{"byte_count":44323,"http_status":200,"request":{"headers":{"User-Agent":"ThermoRoute/1.0 Route-A pre-label meteorology"},"method":"GET","provider":"ornl-daymet-single-pixel-route-a","schema_version":1,"url":"https://daymet.ornl.gov/single-pixel/api/data?lat=34.70097220&lon=-83.72925000&vars=tmax,tmin,prcp,srad,vp&start=2018-01-01&end=2020-12-31"},"request_sha256":"254629b3b7d6a0c5b3554efa14b03e8e335eed1f5263e5ba6da9340ae6d93210","response_file":"response.bin","response_headers":{"Cache-Control":"max-age=1","Connection":"close","Content-Disposition":"attachment; filename=11209_lat_34.7009722_lon_-83.72925_2026-07-21_234516.csv","Content-Length":"44323","Content-Type":"text/csv; charset=utf-8","Date":"Wed, 22 Jul 2026 03:45:15 GMT","Expires":"Wed, 22 Jul 2026 03:45:16 GMT","Server":"Apache","Strict-Transport-Security":"max-age=31536000"},"response_sha256":"3726a01fbc1f7aae899fc640f68fddd877ada59a802fd62288da8f8566213ec1","retrieved_at_utc":"2026-07-22T03:45:16.304754+00:00","schema_version":1}
