{"byte_count":43554,"http_status":200,"request":{"headers":{"User-Agent":"ThermoRoute/1.0 Route-A pre-label meteorology"},"method":"GET","provider":"ornl-daymet-single-pixel-route-a","schema_version":1,"url":"https://daymet.ornl.gov/single-pixel/api/data?lat=45.47678690&lon=-122.49842390&vars=tmax,tmin,prcp,srad,vp&start=2018-01-01&end=2020-12-31"},"request_sha256":"5484bf0afe68e308d4309ea98b386a67dcf485d538d965e6c175f4b6d62f3fd5","response_file":"response.bin","response_headers":{"Cache-Control":"max-age=1","Connection":"close","Content-Disposition":"attachment; filename=12089_lat_45.4767869_lon_-122.4984239_2026-07-21_235324.csv","Content-Length":"43554","Content-Type":"text/csv; charset=utf-8","Date":"Wed, 22 Jul 2026 03:53:24 GMT","Expires":"Wed, 22 Jul 2026 03:53:25 GMT","Server":"Apache","Strict-Transport-Security":"max-age=31536000"},"response_sha256":"079b140bfcd653014704e899f6016e07400063453ce270bc7edca19f87c2621c","retrieved_at_utc":"2026-07-22T03:53:25.051978+00:00","schema_version":1}
