{"byte_count":43509,"http_status":200,"request":{"headers":{"User-Agent":"ThermoRoute/1.0 Route-A pre-label meteorology"},"method":"GET","provider":"ornl-daymet-single-pixel-route-a","schema_version":1,"url":"https://daymet.ornl.gov/single-pixel/api/data?lat=38.74194444&lon=-108.08041667&vars=tmax,tmin,prcp,srad,vp&start=2018-01-01&end=2020-12-31"},"request_sha256":"d4af6ed56297f7ce18d6761c99d8e9c181d5c1814c92218f562801da8bd42e96","response_file":"response.bin","response_headers":{"Cache-Control":"max-age=1","Connection":"close","Content-Disposition":"attachment; filename=11556_lat_38.74194444_lon_-108.08041667_2026-07-21_235014.csv","Content-Length":"43509","Content-Type":"text/csv; charset=utf-8","Date":"Wed, 22 Jul 2026 03:50:14 GMT","Expires":"Wed, 22 Jul 2026 03:50:15 GMT","Server":"Apache","Strict-Transport-Security":"max-age=31536000"},"response_sha256":"93173bb7b72024374a77ce690f98670804cdc3584d7a2363ab5439d5b7737a36","retrieved_at_utc":"2026-07-22T03:50:15.023506+00:00","schema_version":1}
