{"byte_count":49420,"http_status":200,"request":{"headers":{"User-Agent":"ThermoRoute/1.0 Route-A pre-label meteorology"},"method":"GET","provider":"gridmet-ncss-route-a","schema_version":1,"url":"https://thredds.northwestknowledge.net/thredds/ncss/agg_met_vs_1979_CurrentYear_CONUS.nc?var=daily_mean_wind_speed&latitude=25.92600000&longitude=-81.54430560&time_start=2018-01-01T00:00:00Z&time_end=2020-12-31T00:00:00Z&accept=csv"},"request_sha256":"9481d113a4008ad89a533463b4769cd89c2df3c2b336d2282e00ad9febfb5d9f","response_file":"response.bin","response_headers":{"Access-Control-Allow-Origin":"*","Connection":"close","Content-Type":"text/plain;charset=UTF-8","Date":"Wed, 22 Jul 2026 03:53:45 GMT","Server":"Apache-Coyote/1.1","Transfer-Encoding":"chunked"},"response_sha256":"2c1a22fede0e2237bd083e2dc2b871d5ae24d3a68b28073bba75929643e65daa","retrieved_at_utc":"2026-07-22T03:53:58.467919+00:00","schema_version":1}
